gp_dl/__init__.py
gp_dl/cli.py
gp_dl/lib.py
gp_dl-0.3.0.dist-info/licenses/LICENSE
gp_dl-0.3.0.dist-info/METADATA
gp_dl-0.3.0.dist-info/WHEEL
gp_dl-0.3.0.dist-info/entry_points.txt
gp_dl-0.3.0.dist-info/top_level.txt
gp_dl-0.3.0.dist-info/RECORD
