Metadata-Version: 2.4
Name: gp-dl
Version: 0.3.0
Summary: A Python-based Google Photos downloader built with Selenium.
Author-email: csd4ni3l <csd4ni3l@duck.com>
License: GPL v3
Classifier: License :: OSI Approved :: GNU General Public License v3 (GPLv3)
Classifier: Programming Language :: Python :: 3
Classifier: Programming Language :: Python :: 3.11
Classifier: Operating System :: OS Independent
Classifier: Environment :: Console
Classifier: Topic :: Internet :: WWW/HTTP :: Indexing/Search
Classifier: Topic :: Utilities
Requires-Python: >=3.11
License-File: LICENSE
Requires-Dist: selenium>=4.33.0
Dynamic: license-file
